Metadata-Version: 1.1
Name: washer
Version: 0.4
Summary: A whoosh-based CLI indexer and searcher for your files.
Home-page: https://github.com/fiatjaf/washer
Author: UNKNOWN
Author-email: UNKNOWN
License: UNKNOWN
Platform: UNKNOWN
Classifier: Programming Language :: Python :: 3
